wangankeji_sso/__init__.py
wangankeji_sso/client/__init__.py
wangankeji_sso/client/client.py
wangankeji_sso/client/enums.py
wangankeji_sso/client/exceptions.py
wangankeji_sso/client/http.py
wangankeji_sso/client/models.py
wangankeji_sso/client/utils.py
wangankeji_sso-1.5.1.dist-info/METADATA
wangankeji_sso-1.5.1.dist-info/WHEEL
wangankeji_sso-1.5.1.dist-info/top_level.txt
wangankeji_sso-1.5.1.dist-info/RECORD
